<TextureAtlas imagePath="sprites.png">
	<SubTexture name="1.jpg" x="428" y="304" width="105" height="150"/>
	<SubTexture name="2.jpg" x="856" y="608" width="105" height="150"/>
	<SubTexture name="3.jpg" x="856" y="456" width="105" height="150"/>
	<SubTexture name="4.jpg" x="856" y="304" width="105" height="150"/>
	<SubTexture name="5.jpg" x="856" y="152" width="105" height="150"/>
	<SubTexture name="6.jpg" x="856" y="0" width="105" height="150"/>
	<SubTexture name="7.jpg" x="749" y="760" width="105" height="150"/>
	<SubTexture name="8.jpg" x="749" y="608" width="105" height="150"/>
	<SubTexture name="9.jpg" x="749" y="456" width="105" height="150"/>
	<SubTexture name="10.jpg" x="749" y="304" width="105" height="150"/>
	<SubTexture name="11.jpg" x="749" y="152" width="105" height="150"/>
	<SubTexture name="12.jpg" x="749" y="0" width="105" height="150"/>
	<SubTexture name="13.jpg" x="642" y="760" width="105" height="150"/>
	<SubTexture name="14.jpg" x="642" y="608" width="105" height="150"/>
	<SubTexture name="15.jpg" x="642" y="456" width="105" height="150"/>
	<SubTexture name="16.jpg" x="642" y="304" width="105" height="150"/>
	<SubTexture name="17.jpg" x="642" y="152" width="105" height="150"/>
	<SubTexture name="18.jpg" x="642" y="0" width="105" height="150"/>
	<SubTexture name="19.jpg" x="535" y="760" width="105" height="150"/>
	<SubTexture name="20.jpg" x="535" y="608" width="105" height="150"/>
	<SubTexture name="21.jpg" x="535" y="456" width="105" height="150"/>
	<SubTexture name="22.jpg" x="535" y="304" width="105" height="150"/>
	<SubTexture name="23.jpg" x="535" y="152" width="105" height="150"/>
	<SubTexture name="24.jpg" x="535" y="0" width="105" height="150"/>
	<SubTexture name="25.jpg" x="428" y="760" width="105" height="150"/>
	<SubTexture name="26.jpg" x="428" y="608" width="105" height="150"/>
	<SubTexture name="27.jpg" x="428" y="456" width="105" height="150"/>
	<SubTexture name="28.jpg" x="856" y="760" width="105" height="150"/>
	<SubTexture name="29.jpg" x="428" y="152" width="105" height="150"/>
	<SubTexture name="30.jpg" x="428" y="0" width="105" height="150"/>
	<SubTexture name="31.jpg" x="321" y="760" width="105" height="150"/>
	<SubTexture name="32.jpg" x="321" y="608" width="105" height="150"/>
	<SubTexture name="33.jpg" x="321" y="456" width="105" height="150"/>
	<SubTexture name="34.jpg" x="321" y="304" width="105" height="150"/>
	<SubTexture name="35.jpg" x="321" y="152" width="105" height="150"/>
	<SubTexture name="36.jpg" x="321" y="0" width="105" height="150"/>
	<SubTexture name="37.jpg" x="214" y="760" width="105" height="150"/>
	<SubTexture name="38.jpg" x="214" y="608" width="105" height="150"/>
	<SubTexture name="39.jpg" x="214" y="456" width="105" height="150"/>
	<SubTexture name="40.jpg" x="214" y="304" width="105" height="150"/>
	<SubTexture name="41.jpg" x="214" y="152" width="105" height="150"/>
	<SubTexture name="42.jpg" x="214" y="0" width="105" height="150"/>
	<SubTexture name="43.jpg" x="107" y="760" width="105" height="150"/>
	<SubTexture name="44.jpg" x="107" y="608" width="105" height="150"/>
	<SubTexture name="45.jpg" x="107" y="456" width="105" height="150"/>
	<SubTexture name="46.jpg" x="107" y="304" width="105" height="150"/>
	<SubTexture name="47.jpg" x="107" y="152" width="105" height="150"/>
	<SubTexture name="48.jpg" x="107" y="0" width="105" height="150"/>
	<SubTexture name="49.jpg" x="0" y="760" width="105" height="150"/>
	<SubTexture name="50.jpg" x="0" y="608" width="105" height="150"/>
	<SubTexture name="51.jpg" x="0" y="456" width="105" height="150"/>
	<SubTexture name="52.jpg" x="0" y="304" width="105" height="150"/>
	<SubTexture name="53.jpg" x="0" y="152" width="105" height="150"/>
	<SubTexture name="54.jpg" x="0" y="0" width="105" height="150"/>

</TextureAtlas>